pycovid_india/__init__.py
pycovid_india/config.json
pycovid_india/statecode.json
pycovid_india/util.py
pycovid_india-0.0.8.data/data/config/config.json
pycovid_india-0.0.8.data/data/statecode/statecode.json
pycovid_india-0.0.8.dist-info/LICENSE
pycovid_india-0.0.8.dist-info/METADATA
pycovid_india-0.0.8.dist-info/WHEEL
pycovid_india-0.0.8.dist-info/top_level.txt
pycovid_india-0.0.8.dist-info/zip-safe
pycovid_india-0.0.8.dist-info/RECORD
