Metadata-Version: 2.1
Name: pycovid-india
Version: 0.0.8
Summary: Indian COVID-19 Vaccine and Cases Status Information
Home-page: UNKNOWN
Author: T.THAVASI GTI
Author-email: ganeshanthavasigti1032000@gmail.com
License: MIT
Project-URL: Source, https://github.com/THAVASIGTI/pycovid_india.git
Project-URL: download_url, https://github.com/THAVASIGTI/pycovid_india/archive/refs/heads/master.zip
Project-URL: Tracker, https://github.com/THAVASIGTI/pycovid_india/issues
Platform: UNKNOWN
Classifier: Intended Audience :: Developers
Classifier: Intended Audience :: System Administrators
Classifier: Programming Language :: Python :: 3
Classifier: License :: OSI Approved :: MIT License
Classifier: Operating System :: OS Independent
Requires-Python: >=3
License-File: LICENSE
Requires-Dist: requests
